{
  "type": "pfm:furniture",
  "group": "chairs",
  "ingredients": [
    {
      "item": "hybrid-aquatic:driftwood_planks"
    },
    {
      "item": "hybrid-aquatic:driftwood_planks"
    },
    {
      "item": "hybrid-aquatic:stripped_driftwood_log"
    },
    {
      "item": "hybrid-aquatic:stripped_driftwood_log"
    },
    {
      "item": "hybrid-aquatic:stripped_driftwood_log"
    },
    {
      "item": "hybrid-aquatic:stripped_driftwood_log"
    }
  ],
  "result": {
    "count": 4,
    "item": "pfm:stripped_driftwood_hybrid-aquatic_chair"
  }
}